omni_converter/__init__.py
omni_converter/auto_data/__init__.py
omni_converter/auto_data/auto_v2.py
omni_converter/auto_data/auto_v2.pyi
omni_converter/auto_data/default_rules.py
omni_converter/auto_data/format_resolution.py
omni_converter/auto_data/i_auto_data.py
omni_converter/auto_data/i_auto_data.pyi
omni_converter/auto_data/solver.py
omni_converter/coconut/__coconut__.py
omni_converter/coconut/astar.py
omni_converter/coconut/auto_data.py
omni_converter/coconut/monad.py
omni_converter/solver/__init__.py
omni_converter/solver/astar.py
omni_converter/solver/astar.pyi
omni_converter/solver/heap_wrapper.py
omni_converter/solver/rules.py
omni_converter/solver/rules.pyi
omni_converter/util.py
omni_converter/util.pyi
py_omni_converter-0.1.45.dist-info/LICENSE
py_omni_converter-0.1.45.dist-info/METADATA
py_omni_converter-0.1.45.dist-info/WHEEL
py_omni_converter-0.1.45.dist-info/RECORD
