Metadata-Version: 2.1
Name: py-omni-converter
Version: 0.1.45
Summary: 
License: MIT
Author: proboscis
Author-email: nameissoap@gmail.com
Requires-Python: >=3.10,<4.0
Classifier: License :: OSI Approved :: MIT License
Classifier: Programming Language :: Python :: 3
Classifier: Programming Language :: Python :: 3.10
Classifier: Programming Language :: Python :: 3.11
Classifier: Programming Language :: Python :: 3.12
Requires-Dist: cloudpickle (>=3.0.0,<4.0.0)
Requires-Dist: cytoolz
Requires-Dist: loguru
Requires-Dist: lru-dict (>=1.0.0,<2.0.0)
Requires-Dist: pampy
Requires-Dist: tabulate
Requires-Dist: tqdm
